CustomIntents/Bcolor.py
CustomIntents/BinaryImageClassificator.py
CustomIntents/Chatbot.py
CustomIntents/ImageClassificator.py
CustomIntents/ImageGenerator.py
CustomIntents/JsonIntents.py
CustomIntents/Legacy.py
CustomIntents/MusicGan.py
CustomIntents/PLinearRegression.py
CustomIntents/StyleTransformer.py
CustomIntents/Super_Res.py
CustomIntents/__init__.py
CustomIntents/scanner.py
CustomIntents/utils.py
CustomIntents/Pfunction/Pfunctions.py
CustomIntents/Pfunction/__init__.py
CustomIntents/cascades/haarcascade_frontalcatface.xml
CustomIntents-1.0.0.dist-info/LICENSE.md
CustomIntents-1.0.0.dist-info/METADATA
CustomIntents-1.0.0.dist-info/WHEEL
CustomIntents-1.0.0.dist-info/top_level.txt
CustomIntents-1.0.0.dist-info/RECORD
