Metadata-Version: 2.1
Name: CustomIntents
Version: 1.0.0
Home-page: https://github.com/iparsw/custom-intent.git
Author: Parsa Roshanak (iparsw)
Author-email: parsaroshanak@gmail.com
Requires-Python: >=3.9, <=3.11
License-File: LICENSE.md
Requires-Dist: gmpy2 (==2.1.5)
Requires-Dist: gradio (==3.16.2)
Requires-Dist: keras (==2.10.0)
Requires-Dist: Keras-Preprocessing (==1.1.2)
Requires-Dist: matplotlib (==3.6.2)
Requires-Dist: nltk (==3.8)
Requires-Dist: numpy (==1.23.5)
Requires-Dist: opencv-python (==4.7.0.68)
Requires-Dist: setuptools (==65.7.0)
Requires-Dist: tensorflow (==2.10.0)
Requires-Dist: wandb (==0.13.7)
Requires-Dist: music21 (==8.1.0)
Requires-Dist: future (==0.18.2)
Requires-Dist: customtkinter (==5.0.3)
Requires-Dist: pillow (==9.3.0)
